{"paths":{},"types":[],"uuids":["f2cZsdpwpB7IQsFkwv8Ce/","dcGU8ayKVGyqr58Dtwl0r1","550RC5urZNnZQWA+RpBPo1","3e2Ug6031GmYdik5kQw+En","c6tf0Tan9Bh4cWEYnl0Twn","0a8z+LRRJFL4/64Bdc7nZ8","f3d5R3fb9HUZAvmFlzcgFS","80x7HnHfdPx5TlxTBzhCDt","ecpdLyjvZBwrvm+cedCcQy","11uCRMttlFd7N+YnuVInhI","42ZifUFO9HG6/unBZYJRqs","a70y/BSilJHqXiCJIGPTXQ","3ae7efMv1CLq2ilvUY/tQi","97fP6bIcdJjrBgVBgAURqL","32+NzDp8xPjZTpXK7q8q0h","49LBk7l6RC87epam5M7MDp","8fi6VPcPZMoYbZ3dvYXnad"],"scenes":{"db://assets/game.fire":0},"redirect":[8,0,12,0],"deps":["internal"],"name":"main","importBase":"import","nativeBase":"native","debug":false,"isZip":false,"encrypted":false,"versions":{"import":[5,"4b3a3",9,"97d5e",14,"d1312",3,"7871f",10,"83ee2",15,"84ac4",2,"82a07",7,"7871f",16,"8cf88",13,"eb07d",11,"ada2f",4,"7871f",1,"ecaf7",0,"b21b1",6,"7871f"],"native":[5,"0c687",3,"5fdc8",2,"fe7c9",7,"c0cb3",4,"4b0bd",1,"74fd1",6,"c1880"]}}